chanmaster/K.py
chanmaster/chart.py
chanmaster/kService.py
chanmaster/list
chanmaster/myEnum.py
chanmaster/myObject.py
chanmaster/render.py
chanmaster/ta.py
chanmaster/web.py
chanmaster/static/index.html
chanmaster/static/materialize.min-1.0.0.css
chanmaster/static/materialize.min-1.0.0.js
chanmaster-1.0.5.dist-info/METADATA
chanmaster-1.0.5.dist-info/WHEEL
chanmaster-1.0.5.dist-info/top_level.txt
chanmaster-1.0.5.dist-info/RECORD
