Metadata-Version: 2.1
Name: chanmaster
Version: 1.0.5
Summary: UNKNOWN
Home-page: UNKNOWN
Author: UNKNOWN
Author-email: UNKNOWN
License: Apache 2.0
Platform: UNKNOWN
Classifier: Programming Language :: Python :: 3
Requires-Dist: akshare
Requires-Dist: Flask
Requires-Dist: numpy
Requires-Dist: pyecharts
Requires-Dist: Requests
